[{"pageViews": 3360, "socialRefs": 839, "title": "Two killed in crash on Lake Avenue", "ssts": {"topic": "", "section": "news", "subsection": ""}, "publishDate": "2017-01-24T21:06:41.273Z", "siteId": 47, "shares": 0, "_links": {"longUrl": {"href": "http://www.democratandchronicle.com/story/news/2017/01/24/fatal-crash-lake-avenue/97004534/"}}, "type": "text", "id": 97004534}, {"pageViews": 2876, "socialRefs": 713, "title": "Attention readers: We're making some changes to the D&C", "ssts": {"topic": "magnuson", "section": "opinion", "subsection": "columnist"}, "publishDate": "2017-01-24T11:34:48.44Z", "siteId": 47, "shares": 6, "_links": {"longUrl": {"href": "http://www.democratandchronicle.com/story/opinion/columnist/magnuson/2017/01/24/karen-magnuson-making-changes-democrat-chronicle/96826078/"}}, "type": "text", "id": 96826078}, {"pageViews": 2013, "socialRefs": 861, "title": "Historic Greece hotel could fall for gas station", "ssts": {"topic": "", "section": "news", "subsection": ""}, "publishDate": "2017-01-24T20:24:08.763Z", "siteId": 47, "shares": 10, "_links": {"longUrl": {"href": "http://www.democratandchronicle.com/story/news/2017/01/24/historic-greece-hotel-could-fall-gas-station/96983572/"}}, "type": "text", "id": 96983572}, {"pageViews": 1851, "socialRefs": 437, "title": "Schools hit snooze button on later start times", "ssts": {"topic": "", "section": "news", "subsection": ""}, "publishDate": "2017-01-24T20:05:50.437Z", "siteId": 47, "shares": 8, "_links": {"longUrl": {"href": "http://www.democratandchronicle.com/story/news/2017/01/24/school-start-times-sleep-pittsford-brighton/96847072/"}}, "type": "text", "id": 96847072}, {"pageViews": 1580, "socialRefs": 156, "title": "Capelli Sport Stadium new name of Rochester's downtown soccer park", "ssts": {"topic": "", "section": "sports", "subsection": "soccer"}, "publishDate": "2017-01-24T16:37:35.153Z", "siteId": 47, "shares": 2, "_links": {"longUrl": {"href": "http://www.democratandchronicle.com/story/sports/soccer/2017/01/24/capelli-sport-stadium-new-name-rochesters-downtown-soccer-park/96982750/"}}, "type": "text", "id": 96982750}, {"pageViews": 1511, "socialRefs": 128, "title": "Brighton High grad arrested while reporting on protests", "ssts": {"topic": "", "section": "news", "subsection": ""}, "publishDate": "2017-01-24T21:22:12.113Z", "siteId": 47, "shares": 2, "_links": {"longUrl": {"href": "http://www.democratandchronicle.com/story/news/2017/01/24/brighton-high-grad-arrested-while-reporting-protests/96989204/"}}, "type": "text", "id": 96989204}, {"pageViews": 810, "socialRefs": 308, "title": "Nazareth's Stenglein authoring inspirational comeback", "ssts": {"topic": "", "section": "sports", "subsection": "college"}, "publishDate": "2017-01-24T17:18:09.95Z", "siteId": 47, "shares": 0, "_links": {"longUrl": {"href": "http://www.democratandchronicle.com/story/sports/college/2017/01/24/nazareths-stenglein-authoring-inspirational-comeback/96847438/"}}, "type": "text", "id": 96847438}, {"pageViews": 703, "socialRefs": 86, "title": "Audit: charter school has no bidding process", "ssts": {"topic": "", "section": "news", "subsection": ""}, "publishDate": "2017-01-24T15:31:27.047Z", "siteId": 47, "shares": 0, "_links": {"longUrl": {"href": "http://www.democratandchronicle.com/story/news/2017/01/24/rochester-career-mentoring-charter-procurement-audit/96985016/"}}, "type": "text", "id": 96985016}, {"pageViews": 411, "socialRefs": 45, "title": "New RIT president to be announced Wednesday", "ssts": {"topic": "", "section": "news", "subsection": ""}, "publishDate": "2017-01-24T19:05:32.797Z", "siteId": 47, "shares": 0, "_links": {"longUrl": {"href": "http://www.democratandchronicle.com/story/news/2017/01/24/new-rit-president-announced-wednesday/96982206/"}}, "type": "text", "id": 96982206}, {"pageViews": 364, "socialRefs": 4, "title": "Life sentence plus 10 years for murder, drugs", "ssts": {"topic": "", "section": "news", "subsection": ""}, "publishDate": "2017-01-24T20:40:26.887Z", "siteId": 47, "shares": 0, "_links": {"longUrl": {"href": "http://www.democratandchronicle.com/story/news/2017/01/24/life-sentence-plus-10-years-murder-drugs/97003126/"}}, "type": "text", "id": 97003126}]